ipa/sequential/decode.v
`timescale 1ns/10ps

module decode(clk, icode, rA, rB, r0, r1, r2, r3, r4, r5, r6, r7, r8, r9, r10, r11, r12, r13, r14, valA, valB);

//IMP -> you can't input a 2D array like reg_file to a module and so we input each register value on its own

input clk;
input [3:0]icode;
//input ifun[3:0];
input [3:0]rA;
input [3:0]rB;

output reg signed [63:0] r1;
output reg signed [63:0] r2;
output reg signed [63:0] r3;
output reg signed [63:0] r4;
output reg signed [63:0] r5;
output reg signed [63:0] r6;
output reg signed [63:0] r7;
output reg signed [63:0] r8;
output reg signed [63:0] r9;
output reg signed [63:0] r10;
output reg signed [63:0] r11;
output reg signed [63:0] r12;
output reg signed [63:0] r13;
output reg signed [63:0] r14;
output reg signed [63:0] r0;

output reg signed [63:0]valA;
output reg signed [63:0]valB;

reg signed [63:0]reg_file [0:14]; //15 reigsters of size 64 bits

//for the purpose of testing testbench
initial 
begin
reg_file[0] = 64'd5;
reg_file[1] = 64'd45;
reg_file[2] = -64'd90;
reg_file[3] = 64'd54;
reg_file[4] = 64'd32;  //stack pointer register
reg_file[5] = 64'd21;
reg_file[6] = 64'd56;
reg_file[7] = 64'd33;
reg_file[8] = -64'd77;
reg_file[9] = 64'd0;
reg_file[10] = 64'd34;
reg_file[11] = 64'd7;
reg_file[12] = 64'd5;
reg_file[13] = -64'd9;
reg_file[14] = 64'd16;
end

always @(*) //we need to do this at * and not just at posedge of clk because we need to make sure that the value of rA is first fetched and then only can we use it
begin
  case(icode)
    //halt - 4'b0000
    //nop - 4'b0001
    //cmovxx 
    4'b0010:
    begin
        valA = reg_file[rA];
    end

    //irmovq - 4'b0011
    //rmmovq
    4'b0100:
    begin
        valA = reg_file[rA];
        valB = reg_file[rB];
    end

    //mrmovq
    4'b0101:
    begin
        valB = reg_file[rB];
    end

    //opq
    4'b0110:
    begin
        valA = reg_file[rA];
        valB = reg_file[rB];
    end

    //jxx - 4'b0111
    //call
    4'b1000:
    begin
        valB = reg_file[4]; //register 4 is the stack pointer register (rsp)
    end

    //ret
    4'b1001:
    begin
        valA = reg_file[4];
        valB = reg_file[4];
    end

    //pushq
    4'b1010:
    begin
        valA = reg_file[rA];
        valB = reg_file[4];
    end

    //popq
    4'b1011:
    begin
        valA = reg_file[4];
        valB = reg_file[4];
    end
    endcase

    r0 = reg_file[0];
    r1 = reg_file[1];
    r2 = reg_file[2];
    r3 = reg_file[3];
    r4 = reg_file[4]; //stack pointer register
    r5 = reg_file[5];
    r6 = reg_file[6];
    r7 = reg_file[7];
    r8 = reg_file[8];
    r9 = reg_file[9];
    r10 = reg_file[10];
    r11 = reg_file[11];
    r12 = reg_file[12];
    r13 = reg_file[13];
    r14 = reg_file[14];
end

endmodule

ipa/sequential/fetch.v
`timescale 1ns/10ps

module fetch(clk,PC,icode,ifun,rA,rB,valC,valP,in_mem,in_inst,hlt);

//[63:0] after regA makes it an array but putting it before means its a ner
input clk;
input [63:0] PC; //memory address is 64 bits
output reg [3:0]icode; //first 4 bits of the first byte
output reg [3:0]ifun; //last 4 bits of the first byte
output reg [3:0]rA; //first 4 bits of the second byte
output reg [3:0]rB; //last 4 bits of the second byte
output reg signed [63:0]valC; //stores the constant word
output reg [63:0]valP; //stores the address of next instruction (PC should be this value)
output reg in_mem; //invalid memory
output reg in_inst; //invalid instruction
output reg hlt; //inavlid halt

//setting up instruction memory
reg [7:0] instr_mem[0:1023]; //this means we have a 100 rows of 1 byte instructions

reg [0:15]instr; //80 bits of an instruction (maximum size of instruction is 10 bytes)

initial 
begin
//for testing fetch_tb.v

//opq - add
instr_mem[0] = 8'b01100000;
instr_mem[1] = 8'b00010011;

//irmovq
instr_mem[2] = 8'b00110000;
instr_mem[3] = 8'b11110011;
instr_mem[4] = 8'b00000000; //constant - 8 bytes
instr_mem[5] = 8'b00000000;
instr_mem[6] = 8'b00000000;
instr_mem[7] = 8'b00000000;
instr_mem[8] = 8'b00000000;
instr_mem[9] = 8'b00000010;
instr_mem[10] = 8'b00000000;
instr_mem[11] = 8'b00000100;

//pushq
instr_mem[12] = 8'b10100000;
instr_mem[13] = 8'b00111111;

//nop
instr_mem[14] = 8'b00010000;

//opq
instr_mem[15]=8'b01100000;
instr_mem[16]=8'b00100010;

//jump-zf
instr_mem[17]=8'b01110011;
instr_mem[18]=8'b00000000; //constant - 8 bytes
instr_mem[19]=8'b00000000;
instr_mem[20]=8'b00000000;
instr_mem[21]=8'b00000000;
instr_mem[22]=8'b00000000;
instr_mem[23]=8'b00000000;
instr_mem[24]=8'b00000010;
instr_mem[25]=8'b00000000;

//cmov-zf
instr_mem[26]=8'b00100011;
instr_mem[27]=8'b00100010;

//cmov-
instr_mem[28]=8'b00100010;
instr_mem[29]=8'b00100010;

/*
//call
instr_mem[30]=8'b10000000;
instr_mem[31]=8'b00000000; //constant
instr_mem[32]=8'b00000000;
instr_mem[33]=8'b00000000;
instr_mem[34]=8'b00000000;
instr_mem[35]=8'b00000000;
instr_mem[36]=8'b00000000;
instr_mem[37]=8'b00000010;
instr_mem[38]=8'b00000010;
*/

//mrmov
instr_mem[30]=8'b01010000;
instr_mem[31]=8'b00010000;
instr_mem[32]=8'b00000000; //constant
instr_mem[33]=8'b00000000;
instr_mem[34]=8'b00000000;
instr_mem[35]=8'b00000000;
instr_mem[36]=8'b00000000;
instr_mem[37]=8'b00000000;
instr_mem[38]=8'b00000000;
instr_mem[39]=8'b00000010;

//rmmov
instr_mem[40]=8'b01000000;
instr_mem[41]=8'b00010011;
instr_mem[42]=8'b00000000; //constant
instr_mem[43]=8'b00000000;
instr_mem[44]=8'b00000000;
instr_mem[45]=8'b00000000;
instr_mem[46]=8'b00000000;
instr_mem[47]=8'b00000000;
instr_mem[48]=8'b00000000;
instr_mem[49]=8'b00000100;

//call
instr_mem[50]=8'b10000000;
instr_mem[51]=8'b00000000; //constant
instr_mem[52]=8'b00000000;
instr_mem[53]=8'b00000000;
instr_mem[54]=8'b00000000;
instr_mem[55]=8'b00000000;
instr_mem[56]=8'b00000000;
instr_mem[57]=8'b00000000;
instr_mem[58]=8'b11000000;

//nop 
instr_mem[192]=8'b00010000;

//ret
instr_mem[193]=8'b10010000;

//popq
instr_mem[59]=8'b10110000;
instr_mem[60]=8'b00011111;

//halt
instr_mem[61]=8'b00000000;

end

always@(posedge clk)
begin
    in_mem = 1'b0; //invalid memory = 0
    in_inst = 1'b0;
    hlt = 1'b0;

    if(PC > 1023)
    begin
        //this is an invalid instruction
        in_mem = 1'b1;
    end

    //every instruction will be (PC + 10) max length
    instr = {instr_mem[PC],instr_mem[PC+1]};

    icode = instr[0:3];
    ifun = instr[4:7];

    case(icode)
    4'b0000: 
    begin
        hlt = 1'b1; //halt
        valP = PC + 64'd1; //next instruction is at PC + 1
    end

    4'b0001:
    begin
    valP = PC + 64'd1; //nop
    end

    4'b0010:
    begin
    //cmovxx or rrmovq
    rA = instr[8:11]; //first 4 bits of register byte
    rB = instr[12:15];
    valP = PC + 64'd2;
    hlt = 1'b0;
    end

    4'b0011:
    //irmov
    begin
    rA = instr[8:11]; //will be F because it is constant
    rB = instr[12:15];
    valC = {instr_mem[PC+2],instr_mem[PC+3],instr_mem[PC+4],instr_mem[PC+5],instr_mem[PC+6],instr_mem[PC+7],instr_mem[PC+8],instr_mem[PC+9]};
    valP = PC + 64'd10;
    hlt = 1'b0;
    end

    4'b0011:
    //irmov
    begin
    rA = instr[8:11];
    rB = instr[12:15];
    valC = {instr_mem[PC+2],instr_mem[PC+3],instr_mem[PC+4],instr_mem[PC+5],instr_mem[PC+6],instr_mem[PC+7],instr_mem[PC+8],instr_mem[PC+9]};
    valP = PC + 64'd10;
    hlt = 1'b0;
    end

    4'b0100:
    //rmmov
    begin
    rA = instr[8:11];
    rB = instr[12:15];
    valC = {instr_mem[PC+2],instr_mem[PC+3],instr_mem[PC+4],instr_mem[PC+5],instr_mem[PC+6],instr_mem[PC+7],instr_mem[PC+8],instr_mem[PC+9]};
    valP = PC + 64'd10;
    hlt = 1'b0;
    end

    4'b0101:
    //mrmov
    begin
    rA = instr[8:11];
    rB = instr[12:15];
    valC = {instr_mem[PC+2],instr_mem[PC+3],instr_mem[PC+4],instr_mem[PC+5],instr_mem[PC+6],instr_mem[PC+7],instr_mem[PC+8],instr_mem[PC+9]};
    valP = PC + 64'd10;
    hlt = 1'b0;
    end

    4'b0110:
    //op
    begin
    rA = instr[8:11];
    rB = instr[12:15];
    valP = PC + 64'd2;
    hlt = 1'b0;
    end

    4'b0111:
    //jXX
    begin
    valC = {instr_mem[PC+1],instr_mem[PC+2],instr_mem[PC+3],instr_mem[PC+4],instr_mem[PC+5],instr_mem[PC+6],instr_mem[PC+7],instr_mem[PC+8]};
    valP = PC + 64'd9;
    hlt = 1'b0;
    end

    4'b1000:
    //call
    begin
    valC = {instr_mem[PC+1],instr_mem[PC+2],instr_mem[PC+3],instr_mem[PC+4],instr_mem[PC+5],instr_mem[PC+6],instr_mem[PC+7],instr_mem[PC+8]};
    valP = PC + 64'd9;
    hlt = 1'b0;
    end

    4'b1001:
    begin
    //ret
    valP = PC + 64'd1;
    hlt = 1'b0;
    end

    4'b1001:
    begin
    //ret
    valP = PC + 64'd1;
    hlt = 1'b0;
    end

    4'b1010:
    begin
        //push
        rA = instr[8:11];
        rB = instr[12:15];
        valP = PC + 64'd2;
        hlt = 1'b0;
    end

    4'b1011:
    begin
        //push
        rA = instr[8:11];
        rB = instr[12:15];
        valP = PC + 64'd2;
        hlt = 1'b0;
    end

    default:
    begin
    in_inst = 1'b1;//the instruction is invalid
    hlt = 1'b0; 
    end
    endcase
end
endmodule

ipa/sequential/decode_tb.v
`timescale 1ns/10ps
`include "fetch.v"
module decode_tb;

reg clk;
reg [63:0]PC; //memory address is 64 bits
wire [3:0]icode; //first 4 bits of the first byte
wire [3:0]ifun; //last 4 bits of the first byte
wire [3:0]rA; //first 4 bits of the second byte
wire [3:0]rB; //last 4 bits of the second byte
wire signed [63:0]valC; //stores the constant word
wire [63:0]valP; //stores the address of next instruction (PC should be this value)
wire in_mem;
wire in_inst;
wire hlt;
wire signed [63:0] valA;
wire signed [63:0] valB;

wire signed[63:0] r1;
wire signed[63:0] r2;
wire signed[63:0] r3;
wire signed[63:0] r4;
wire signed[63:0] r5;
wire signed[63:0] r6;
wire signed[63:0] r7;
wire signed[63:0] r8;
wire signed[63:0] r9;
wire signed[63:0] r10;
wire signed[63:0] r11;
wire signed[63:0] r12;
wire signed[63:0] r13;
wire signed[63:0] r14;
wire signed[63:0] r0;


fetch UUTA (clk,PC,icode,ifun,rA,rB,valC,valP,in_mem,in_inst,hlt);
decode UUTB (clk, icode, rA, rB, r0, r1, r2, r3, r4, r5, r6, r7, r8, r9, r10, r11, r12, r13, r14, valA, valB); 

initial
    begin
        $dumpfile("decode_tb.vcd");
        $dumpvars(0,decode_tb);
        
        clk = 0;
        PC = 64'd0;

       #10 clk = ~clk; //positive edge 
            PC = 64'd0;
        #10 clk = ~clk; //negative edge so nothing happens
        #10 clk = ~clk;
            PC = valP;
        #10 clk = ~clk;
        #10 clk = ~clk;
            PC = valP;
        #10 clk = ~clk;
        #10 clk = ~clk;
            PC = valP;
        #10 clk = ~clk;
        #10 clk = ~clk;
            PC = valP;
        #10 clk = ~clk;    
        #10 clk = ~clk;
            PC = valP;
        #10 clk = ~clk;    
        #10 clk = ~clk;
            PC = valP;
        #10 clk = ~clk;    
        #10 clk = ~clk;
            PC = valP;
        #10 clk = ~clk;    
        #10 clk = ~clk;
            PC = valP;
        #10 clk = ~clk;    
        #10 clk = ~clk;
            PC = valP;
        #10 clk = ~clk;    
        #10 clk = ~clk;
            PC = valP;
        #10 clk = ~clk;    
        #10 clk = ~clk;
            PC = valP;
        #10 clk = ~clk;    
        #10 clk = ~clk;
            PC = valP;
        #10 clk = ~clk;    
        #10 clk = ~clk;
            PC = valP;
        #10 clk = ~clk;    
        #10 clk = ~clk;
            PC = valP;
    end

initial
    $monitor("clk=%d icode=%b rA=%b rB=%b valA=%d valB=%d \n r0=%d r1=%d r2=%d r3=%d r4=%d r5=%d r6=%d r7=%d \n r8=%d r9=%d r10=%d r11=%d r12=%d r13=%d r14=%d",clk,icode,rA,rB,valA,valB,r0,r1,r2,r3,r4,r5,r6,r7,r8,r9,r10,r11,r12,r13,r14);

endmodule

ipa/sequential/decode_tb.vcd
$date
	Wed Mar  8 23:29:05 2023
$end
$version
	Icarus Verilog
$end
$timescale
	10ps
$end
$scope module decode_tb $end
$var wire 64 ! valP [63:0] $end
$var wire 64 " valC [63:0] $end
$var wire 64 # valB [63:0] $end
$var wire 64 $ valA [63:0] $end
$var wire 4 % rB [3:0] $end
$var wire 4 & rA [3:0] $end
$var wire 64 ' r9 [63:0] $end
$var wire 64 ( r8 [63:0] $end
$var wire 64 ) r7 [63:0] $end
$var wire 64 * r6 [63:0] $end
$var wire 64 + r5 [63:0] $end
$var wire 64 , r4 [63:0] $end
$var wire 64 - r3 [63:0] $end
$var wire 64 . r2 [63:0] $end
$var wire 64 / r14 [63:0] $end
$var wire 64 0 r13 [63:0] $end
$var wire 64 1 r12 [63:0] $end
$var wire 64 2 r11 [63:0] $end
$var wire 64 3 r10 [63:0] $end
$var wire 64 4 r1 [63:0] $end
$var wire 64 5 r0 [63:0] $end
$var wire 1 6 in_mem $end
$var wire 1 7 in_inst $end
$var wire 4 8 ifun [3:0] $end
$var wire 4 9 icode [3:0] $end
$var wire 1 : hlt $end
$var reg 64 ; PC [63:0] $end
$var reg 1 < clk $end
$scope module UUTA $end
$var wire 64 = PC [63:0] $end
$var wire 1 < clk $end
$var reg 1 : hlt $end
$var reg 4 > icode [3:0] $end
$var reg 4 ? ifun [3:0] $end
$var reg 1 7 in_inst $end
$var reg 1 6 in_mem $end
$var reg 16 @ instr [0:15] $end
$var reg 4 A rA [3:0] $end
$var reg 4 B rB [3:0] $end
$var reg 64 C valC [63:0] $end
$var reg 64 D valP [63:0] $end
$upscope $end
$scope module UUTB $end
$var wire 1 < clk $end
$var wire 4 E icode [3:0] $end
$var wire 4 F rA [3:0] $end
$var wire 4 G rB [3:0] $end
$var reg 64 H r0 [63:0] $end
$var reg 64 I r1 [63:0] $end
$var reg 64 J r10 [63:0] $end
$var reg 64 K r11 [63:0] $end
$var reg 64 L r12 [63:0] $end
$var reg 64 M r13 [63:0] $end
$var reg 64 N r14 [63:0] $end
$var reg 64 O r2 [63:0] $end
$var reg 64 P r3 [63:0] $end
$var reg 64 Q r4 [63:0] $end
$var reg 64 R r5 [63:0] $end
$var reg 64 S r6 [63:0] $end
$var reg 64 T r7 [63:0] $end
$var reg 64 U r8 [63:0] $end
$var reg 64 V r9 [63:0] $end
$var reg 64 W valA [63:0] $end
$var reg 64 X valB [63:0] $end
$upscope $end
$upscope $end
$enddefinitions $end
#0
$dumpvars
bx X
bx W
b0 V
b1111111111111111111111111111111111111111111111111111111110110011 U
b100001 T
b111000 S
b10101 R
b100000 Q
b110110 P
b1111111111111111111111111111111111111111111111111111111110100110 O
b10000 N
b1111111111111111111111111111111111111111111111111111111111110111 M
b101 L
b111 K
b100010 J
b101101 I
b101 H
bx G
bx F
bx E
bx D
bx C
bx B
bx A
bx @
bx ?
bx >
b0 =
0<
b0 ;
x:
bx 9
bx 8
x7
x6
b101 5
b101101 4
b100010 3
b111 2
b101 1
b1111111111111111111111111111111111111111111111111111111111110111 0
b10000 /
b1111111111111111111111111111111111111111111111111111111110100110 .
b110110 -
b100000 ,
b10101 +
b111000 *
b100001 )
b1111111111111111111111111111111111111111111111111111111110110011 (
b0 '
bx &
bx %
bx $
bx #
bx "
bx !
$end
#1000
b110110 #
b110110 X
b101101 $
b101101 W
b10 !
b10 D
b11 %
b11 B
b11 G
b1 &
b1 A
b1 F
b0 8
b0 ?
b110 9
b110 >
b110 E
b110000000010011 @
0:
07
06
1<
#2000
0<
#3000
b1100 !
b1100 D
b100000000000000100 "
b100000000000000100 C
b1111 &
b1111 A
b1111 F
b11 9
b11 >
b11 E
b11000011110011 @
b10 ;
b10 =
1<
#4000
0<
#5000
b100000 #
b100000 X
b110110 $
b110110 W
b1110 !
b1110 D
b1111 %
b1111 B
b1111 G
b11 &
b11 A
b11 F
b1010 9
b1010 >
b1010 E
b1010000000111111 @
b1100 ;
b1100 =
1<
#6000
0<
#7000
b1111 !
b1111 D
b1 9
b1 >
b1 E
b1000001100000 @
b1110 ;
b1110 =
1<
#8000
0<
#9000
b1111111111111111111111111111111111111111111111111111111110100110 #
b1111111111111111111111111111111111111111111111111111111110100110 X
b1111111111111111111111111111111111111111111111111111111110100110 $
b1111111111111111111111111111111111111111111111111111111110100110 W
b10001 !
b10001 D
b10 %
b10 B
b10 G
b10 &
b10 A
b10 F
b110 9
b110 >
b110 E
b110000000100010 @
b1111 ;
b1111 =
1<
#10000
0<
#11000
b11010 !
b11010 D
b1000000000 "
b1000000000 C
b11 8
b11 ?
b111 9
b111 >
b111 E
b111001100000000 @
b10001 ;
b10001 =
1<
#12000
0<
#13000
b11100 !
b11100 D
b10 9
b10 >
b10 E
b10001100100010 @
b11010 ;
b11010 =
1<
#14000
0<
#15000
b11110 !
b11110 D
b10 8
b10 ?
b10001000100010 @
b11100 ;
b11100 =
1<
#16000
0<
#17000
b101 #
b101 X
b101000 !
b101000 D
b10 "
b10 C
b0 %
b0 B
b0 G
b1 &
b1 A
b1 F
b0 8
b0 ?
b101 9
b101 >
b101 E
b101000000010000 @
b11110 ;
b11110 =
1<
#18000
0<
#19000
b110110 #
b110110 X
b101101 $
b101101 W
b110010 !
b110010 D
b100 "
b100 C
b11 %
b11 B
b11 G
b100 9
b100 >
b100 E
b100000000010011 @
b101000 ;
b101000 =
1<
#20000
0<
#21000
b100000 #
b100000 X
b111011 !
b111011 D
b11000000 "
b11000000 C
b1000 9
b1000 >
b1000 E
b1000000000000000 @
b110010 ;
b110010 =
1<
#22000
0<
#23000
b100000 $
b100000 W
b111101 !
b111101 D
b1111 %
b1111 B
b1111 G
b1011 9
b1011 >
b1011 E
b1011000000011111 @
b111011 ;
b111011 =
1<
#24000
0<
#25000
b111110 !
b111110 D
1:
b0 9
b0 >
b0 E
b0xxxxxxxx @
b111101 ;
b111101 =
1<
#26000
0<
#27000
17
bx 8
bx ?
bx 9
bx >
bx E
bx @
0:
b111110 ;
b111110 =
1<
#28000
0<
#29000
17
1<
