ipa/sequential/fetch.v
`timescale 1ns/10ps

module fetch(clk,PC,icode,ifun,rA,rB,valC,valP,in_mem,in_inst,hlt);

//[63:0] after regA makes it an array but putting it before means its a ner
input clk;
input [63:0] PC; //memory address is 64 bits
output reg [3:0]icode; //first 4 bits of the first byte
output reg [3:0]ifun; //last 4 bits of the first byte
output reg [3:0]rA; //first 4 bits of the second byte
output reg [3:0]rB; //last 4 bits of the second byte
output reg signed [63:0]valC; //stores the constant word
output reg [63:0]valP; //stores the address of next instruction (PC should be this value)
output reg in_mem; //invalid memory
output reg in_inst; //invalid instruction
output reg hlt; //inavlid halt

//setting up instruction memory
reg [7:0] instr_mem[0:1023]; //this means we have a 100 rows of 1 byte instructions

reg [0:15]instr; //80 bits of an instruction (maximum size of instruction is 10 bytes)

initial 
begin
//for testing fetch_tb.v

//opq - add
instr_mem[0] = 8'b01100000;
instr_mem[1] = 8'b00010011;

//irmovq
instr_mem[2] = 8'b00110000;
instr_mem[3] = 8'b11110011;
instr_mem[4] = 8'b00000000; //constant - 8 bytes
instr_mem[5] = 8'b00000000;
instr_mem[6] = 8'b00000000;
instr_mem[7] = 8'b00000000;
instr_mem[8] = 8'b00000000;
instr_mem[9] = 8'b00000010;
instr_mem[10] = 8'b00000000;
instr_mem[11] = 8'b00000100;

//pushq
instr_mem[12] = 8'b10100000;
instr_mem[13] = 8'b00111111;

//nop
instr_mem[14] = 8'b00010000;

//opq
instr_mem[15]=8'b01100000;
instr_mem[16]=8'b00100010;

//jump-zf
instr_mem[17]=8'b01110011;
instr_mem[18]=8'b00000000; //constant - 8 bytes
instr_mem[19]=8'b00000000;
instr_mem[20]=8'b00000000;
instr_mem[21]=8'b00000000;
instr_mem[22]=8'b00000000;
instr_mem[23]=8'b00000000;
instr_mem[24]=8'b00000010;
instr_mem[25]=8'b00000000;

//cmov-zf
instr_mem[26]=8'b00100011;
instr_mem[27]=8'b00100010;

//cmov-
instr_mem[28]=8'b00100010;
instr_mem[29]=8'b00100010;

/*
//call
instr_mem[30]=8'b10000000;
instr_mem[31]=8'b00000000; //constant
instr_mem[32]=8'b00000000;
instr_mem[33]=8'b00000000;
instr_mem[34]=8'b00000000;
instr_mem[35]=8'b00000000;
instr_mem[36]=8'b00000000;
instr_mem[37]=8'b00000010;
instr_mem[38]=8'b00000010;
*/

//mrmov
instr_mem[30]=8'b01010000;
instr_mem[31]=8'b00010000;
instr_mem[32]=8'b00000000; //constant
instr_mem[33]=8'b00000000;
instr_mem[34]=8'b00000000;
instr_mem[35]=8'b00000000;
instr_mem[36]=8'b00000000;
instr_mem[37]=8'b00000000;
instr_mem[38]=8'b00000000;
instr_mem[39]=8'b00000010;

//rmmov
instr_mem[40]=8'b01000000;
instr_mem[41]=8'b00010011;
instr_mem[42]=8'b00000000; //constant
instr_mem[43]=8'b00000000;
instr_mem[44]=8'b00000000;
instr_mem[45]=8'b00000000;
instr_mem[46]=8'b00000000;
instr_mem[47]=8'b00000000;
instr_mem[48]=8'b00000000;
instr_mem[49]=8'b00000100;

//call
instr_mem[50]=8'b10000000;
instr_mem[51]=8'b00000000; //constant
instr_mem[52]=8'b00000000;
instr_mem[53]=8'b00000000;
instr_mem[54]=8'b00000000;
instr_mem[55]=8'b00000000;
instr_mem[56]=8'b00000000;
instr_mem[57]=8'b00000000;
instr_mem[58]=8'b11000000;

//nop 
instr_mem[192]=8'b00010000;

//ret
instr_mem[193]=8'b10010000;

//popq
instr_mem[59]=8'b10110000;
instr_mem[60]=8'b00011111;

//halt
instr_mem[61]=8'b00000000;

end

always@(posedge clk)
begin
    in_mem = 1'b0; //invalid memory = 0
    in_inst = 1'b0;
    hlt = 1'b0;

    if(PC > 1023)
    begin
        //this is an invalid instruction
        in_mem = 1'b1;
    end

    //every instruction will be (PC + 10) max length
    instr = {instr_mem[PC],instr_mem[PC+1]};

    icode = instr[0:3];
    ifun = instr[4:7];

    case(icode)
    4'b0000: 
    begin
        hlt = 1'b1; //halt
        valP = PC + 64'd1; //next instruction is at PC + 1
    end

    4'b0001:
    begin
    valP = PC + 64'd1; //nop
    end

    4'b0010:
    begin
    //cmovxx or rrmovq
    rA = instr[8:11]; //first 4 bits of register byte
    rB = instr[12:15];
    valP = PC + 64'd2;
    hlt = 1'b0;
    end

    4'b0011:
    //irmov
    begin
    rA = instr[8:11]; //will be F because it is constant
    rB = instr[12:15];
    valC = {instr_mem[PC+2],instr_mem[PC+3],instr_mem[PC+4],instr_mem[PC+5],instr_mem[PC+6],instr_mem[PC+7],instr_mem[PC+8],instr_mem[PC+9]};
    valP = PC + 64'd10;
    hlt = 1'b0;
    end

    4'b0011:
    //irmov
    begin
    rA = instr[8:11];
    rB = instr[12:15];
    valC = {instr_mem[PC+2],instr_mem[PC+3],instr_mem[PC+4],instr_mem[PC+5],instr_mem[PC+6],instr_mem[PC+7],instr_mem[PC+8],instr_mem[PC+9]};
    valP = PC + 64'd10;
    hlt = 1'b0;
    end

    4'b0100:
    //rmmov
    begin
    rA = instr[8:11];
    rB = instr[12:15];
    valC = {instr_mem[PC+2],instr_mem[PC+3],instr_mem[PC+4],instr_mem[PC+5],instr_mem[PC+6],instr_mem[PC+7],instr_mem[PC+8],instr_mem[PC+9]};
    valP = PC + 64'd10;
    hlt = 1'b0;
    end

    4'b0101:
    //mrmov
    begin
    rA = instr[8:11];
    rB = instr[12:15];
    valC = {instr_mem[PC+2],instr_mem[PC+3],instr_mem[PC+4],instr_mem[PC+5],instr_mem[PC+6],instr_mem[PC+7],instr_mem[PC+8],instr_mem[PC+9]};
    valP = PC + 64'd10;
    hlt = 1'b0;
    end

    4'b0110:
    //op
    begin
    rA = instr[8:11];
    rB = instr[12:15];
    valP = PC + 64'd2;
    hlt = 1'b0;
    end

    4'b0111:
    //jXX
    begin
    valC = {instr_mem[PC+1],instr_mem[PC+2],instr_mem[PC+3],instr_mem[PC+4],instr_mem[PC+5],instr_mem[PC+6],instr_mem[PC+7],instr_mem[PC+8]};
    valP = PC + 64'd9;
    hlt = 1'b0;
    end

    4'b1000:
    //call
    begin
    valC = {instr_mem[PC+1],instr_mem[PC+2],instr_mem[PC+3],instr_mem[PC+4],instr_mem[PC+5],instr_mem[PC+6],instr_mem[PC+7],instr_mem[PC+8]};
    valP = PC + 64'd9;
    hlt = 1'b0;
    end

    4'b1001:
    begin
    //ret
    valP = PC + 64'd1;
    hlt = 1'b0;
    end

    4'b1001:
    begin
    //ret
    valP = PC + 64'd1;
    hlt = 1'b0;
    end

    4'b1010:
    begin
        //push
        rA = instr[8:11];
        rB = instr[12:15];
        valP = PC + 64'd2;
        hlt = 1'b0;
    end

    4'b1011:
    begin
        //push
        rA = instr[8:11];
        rB = instr[12:15];
        valP = PC + 64'd2;
        hlt = 1'b0;
    end

    default:
    begin
    in_inst = 1'b1;//the instruction is invalid
    hlt = 1'b0; 
    end
    endcase
end
endmodule

ipa/sequential/fetch_tb.v
`timescale 1ns/10ps

module fetch_tb;

reg clk;
reg [63:0]PC; //memory address is 64 bits
wire [3:0]icode; //first 4 bits of the first byte
wire [3:0]ifun; //last 4 bits of the first byte
wire [3:0]rA; //first 4 bits of the second byte
wire [3:0]rB; //last 4 bits of the second byte
wire signed [63:0]valC; //stores the constant word
wire [63:0]valP; //stores the address of next instruction (PC should be this value)
wire in_mem;
wire in_inst;
wire hlt;

fetch UUT (clk,PC,icode,ifun,rA,rB,valC,valP,in_mem,in_inst,hlt);

initial
    begin
        $dumpfile("fetch_tb.vcd");
        $dumpvars(0,fetch_tb);
        
        clk = 0;
        PC = 64'd0;

        #10 clk = ~clk; //positive edge 
            PC = 64'd0;
        #10 clk = ~clk; //negative edge so nothing happens
        #10 clk = ~clk;
            PC = valP;
        #10 clk = ~clk;
        #10 clk = ~clk;
            PC = valP;
        #10 clk = ~clk;
        #10 clk = ~clk;
            PC = valP;
        #10 clk = ~clk;
        #10 clk = ~clk;
            PC = valP;
        #10 clk = ~clk;    
        #10 clk = ~clk;
            PC = valP;
        #10 clk = ~clk;    
        #10 clk = ~clk;
            PC = valP;
        #10 clk = ~clk;    
        #10 clk = ~clk;
            PC = valP;
        #10 clk = ~clk;    
        #10 clk = ~clk;
            PC = valP;
        #10 clk = ~clk;    
        #10 clk = ~clk;
            PC = valP;
        #10 clk = ~clk;    
        #10 clk = ~clk;
            PC = valP;
        #10 clk = ~clk;    
        #10 clk = ~clk;
            PC = valP;
        #10 clk = ~clk;    
        #10 clk = ~clk;
            PC = valP;
        #10 clk = ~clk;    
        #10 clk = ~clk;
            PC = valP;
        #10 clk = ~clk;    
        #10 clk = ~clk;
            PC = valP;
    end

// always @(Z)
initial
    $monitor("clk=%d  PC = %d  icode=%b  ifun=%b  rA=%b  rB=%b  valC=%d  valP=%d  in_mem=%b  in_inst=%b  hlt=%b",clk,PC,icode,ifun,rA,rB,valC,valP,in_mem,in_inst,hlt);

endmodule

ipa/sequential/fetch_tb.vcd
$date
	Wed Mar  8 23:25:51 2023
$end
$version
	Icarus Verilog
$end
$timescale
	10ps
$end
$scope module fetch_tb $end
$var wire 64 ! valP [63:0] $end
$var wire 64 " valC [63:0] $end
$var wire 4 # rB [3:0] $end
$var wire 4 $ rA [3:0] $end
$var wire 1 % in_mem $end
$var wire 1 & in_inst $end
$var wire 4 ' ifun [3:0] $end
$var wire 4 ( icode [3:0] $end
$var wire 1 ) hlt $end
$var reg 64 * PC [63:0] $end
$var reg 1 + clk $end
$scope module UUT $end
$var wire 64 , PC [63:0] $end
$var wire 1 + clk $end
$var reg 1 ) hlt $end
$var reg 4 - icode [3:0] $end
$var reg 4 . ifun [3:0] $end
$var reg 1 & in_inst $end
$var reg 1 % in_mem $end
$var reg 16 / instr [0:15] $end
$var reg 4 0 rA [3:0] $end
$var reg 4 1 rB [3:0] $end
$var reg 64 2 valC [63:0] $end
$var reg 64 3 valP [63:0] $end
$upscope $end
$upscope $end
$enddefinitions $end
#0
$dumpvars
bx 3
bx 2
bx 1
bx 0
bx /
bx .
bx -
b0 ,
0+
b0 *
x)
bx (
bx '
x&
x%
bx $
bx #
bx "
bx !
$end
#1000
b10 !
b10 3
b11 #
b11 1
b1 $
b1 0
b0 '
b0 .
b110 (
b110 -
b110000000010011 /
0)
0&
0%
1+
#2000
0+
#3000
b1100 !
b1100 3
b100000000000000100 "
b100000000000000100 2
b1111 $
b1111 0
b11 (
b11 -
b11000011110011 /
b10 *
b10 ,
1+
#4000
0+
#5000
b1110 !
b1110 3
b1111 #
b1111 1
b11 $
b11 0
b1010 (
b1010 -
b1010000000111111 /
b1100 *
b1100 ,
1+
#6000
0+
#7000
b1111 !
b1111 3
b1 (
b1 -
b1000001100000 /
b1110 *
b1110 ,
1+
#8000
0+
#9000
b10001 !
b10001 3
b10 #
b10 1
b10 $
b10 0
b110 (
b110 -
b110000000100010 /
b1111 *
b1111 ,
1+
#10000
0+
#11000
b11010 !
b11010 3
b1000000000 "
b1000000000 2
b11 '
b11 .
b111 (
b111 -
b111001100000000 /
b10001 *
b10001 ,
1+
#12000
0+
#13000
b11100 !
b11100 3
b10 (
b10 -
b10001100100010 /
b11010 *
b11010 ,
1+
#14000
0+
#15000
b11110 !
b11110 3
b10 '
b10 .
b10001000100010 /
b11100 *
b11100 ,
1+
#16000
0+
#17000
b101000 !
b101000 3
b10 "
b10 2
b0 #
b0 1
b1 $
b1 0
b0 '
b0 .
b101 (
b101 -
b101000000010000 /
b11110 *
b11110 ,
1+
#18000
0+
#19000
b110010 !
b110010 3
b100 "
b100 2
b11 #
b11 1
b100 (
b100 -
b100000000010011 /
b101000 *
b101000 ,
1+
#20000
0+
#21000
b111011 !
b111011 3
b11000000 "
b11000000 2
b1000 (
b1000 -
b1000000000000000 /
b110010 *
b110010 ,
1+
#22000
0+
#23000
b111101 !
b111101 3
b1111 #
b1111 1
b1011 (
b1011 -
b1011000000011111 /
b111011 *
b111011 ,
1+
#24000
0+
#25000
b111110 !
b111110 3
1)
b0 (
b0 -
b0xxxxxxxx /
b111101 *
b111101 ,
1+
#26000
0+
#27000
1&
bx '
bx .
bx (
bx -
bx /
0)
b111110 *
b111110 ,
1+
#28000
0+
#29000
1&
1+
